{
  "under_35": {
    "neutral": [
      "길에서 번호 한 번쯤은 따이실 법한 얼굴입니다",
      "첫인상에서 일단 손해는 안 보고 들어가는 타입입니다",
      "호감도 기본값이 생각보다 꽤 높은 얼굴입니다",
      "사진보다 실물이 더 낫다는 말을 들을 여지가 있습니다",
      "분위기로 점수 벌 줄 아는 얼굴입니다",
      "꾸몄을 때 반응이 바로 올 얼굴입니다",
      "이목구비보다 전체 분위기가 더 잘 먹히는 타입입니다",
      "무난한 듯 보이지만 은근히 기억에 남는 얼굴입니다"
    ],
    "male": [
      "소개팅 첫 만남에서 최소한 감점부터 먹고 들어가진 않습니다",
      "담백하게 생겼는데 은근히 호감 쌓이는 얼굴입니다",
      "과하게 꾸미지 않아도 기본 인상은 꽤 방어되는 타입입니다",
      "친해질수록 얼굴 점수가 올라갈 타입입니다",
      "남친상이라는 말이 완전히 허위 광고는 아닙니다",
      "선한 인상이 있어서 첫 대화 진입 장벽은 낮은 편입니다",
      "깔끔한 이미지로 주변 반응을 끌어낼 얼굴입니다",
      "부담스럽지 않은 호감형으로 분류해도 무리가 없습니다"
    ],
    "female": [
      "은근히 계속 보게 되는 분위기가 있는 얼굴입니다",
      "첫인상에서 부드러운 호감은 확실히 가져갑니다",
      "꾸미는 맛이 꽤 나는 얼굴입니다",
      "단톡방 프사 바꾸면 누가 물어볼 만한 얼굴입니다",
      "예쁘다는 말이 과장은 아니고 방향성은 확실히 있습니다",
      "화려함보다 분위기로 설득하는 타입입니다",
      "자연스러운 웃음에서 점수가 꽤 오르는 얼굴입니다",
      "호감형이라는 단어를 붙여도 크게 무리 없는 인상입니다"
    ]
  },
  "over_35": {
    "neutral": [
      "나이대 안에서 꽤 안정적으로 호감 주는 얼굴입니다",
      "첫인상에서 신뢰감은 확실히 가져가는 타입입니다",
      "편안한 분위기로 점수를 버는 얼굴입니다",
      "과시하지 않아도 인상이 무너지지 않는 편입니다",
      "자연스러운 연륜이 장점으로 보이는 얼굴입니다",
      "동창회에서 생각보다 관리 잘했다는 말 들을 수 있습니다",
      "차분한 호감이 있어서 대화 전 분위기는 괜찮습니다",
      "튀지는 않지만 오래 볼수록 안정감이 남는 인상입니다"
    ],
    "male": [
      "중년의 안정감이 꽤 괜찮게 남아 있는 얼굴입니다",
      "첫인상에서 믿고 맡겨도 될 것 같은 분위기가 있습니다",
      "과하게 힘주지 않아도 신뢰감은 살아있는 타입입니다",
      "회식 자리에서 어색하지 않게 중심 잡을 인상입니다",
      "깔끔한 이미지가 호감도를 충분히 방어하는 얼굴입니다",
      "무게감과 편안함이 같이 보이는 얼굴입니다",
      "대화가 붙으면 얼굴 점수까지 같이 올라갈 타입입니다",
      "나이대 대비 인상 관리가 꽤 되는 편입니다"
    ],
    "female": [
      "차분하고 단정한 호감이 남는 얼굴입니다",
      "관리된 분위기가 있어서 첫인상은 안정적입니다",
      "화려함보다 우아한 쪽으로 강점이 있는 타입입니다",
      "동창회에서 은근히 시선 받을 만한 분위기는 있습니다",
      "부드러운 인상이 살아 있어서 대화 전 호감이 생깁니다",
      "자연스러운 연륜이 단점보다 장점으로 보이는 얼굴입니다",
      "깔끔한 스타일링과 잘 맞는 인상입니다",
      "나이대 안에서 꽤 좋은 인상으로 분류됩니다"
    ]
  }
}
